cinemark/__init__.py
cinemark/api.py
cinemark_python-0.0.6.dist-info/DESCRIPTION.rst
cinemark_python-0.0.6.dist-info/METADATA
cinemark_python-0.0.6.dist-info/RECORD
cinemark_python-0.0.6.dist-info/WHEEL
cinemark_python-0.0.6.dist-info/metadata.json
cinemark_python-0.0.6.dist-info/top_level.txt
