Metadata-Version: 2.0
Name: cinemark-python
Version: 0.0.6
Summary: Wrapper for Cinemark Brasil API
Home-page: https://github.com/ArrowsX/cinemark-python
Author: Tafarel Yan
Author-email: tafarel.yan@gmail.com
License: UNKNOWN
Platform: UNKNOWN
Requires-Dist: requests
